mautrix/__init__.py
mautrix/api.py
mautrix/fixmodule.py
mautrix/genall.py
mautrix/py.typed
mautrix/appservice/__init__.py
mautrix/appservice/appservice.py
mautrix/appservice/as_handler.py
mautrix/appservice/api/__init__.py
mautrix/appservice/api/appservice.py
mautrix/appservice/api/intent.py
mautrix/appservice/state_store/__init__.py
mautrix/appservice/state_store/asyncpg.py
mautrix/appservice/state_store/file.py
mautrix/appservice/state_store/memory.py
mautrix/bridge/__init__.py
mautrix/bridge/bridge.py
mautrix/bridge/config.py
mautrix/bridge/crypto_state_store.py
mautrix/bridge/custom_puppet.py
mautrix/bridge/disappearing_message.py
mautrix/bridge/e2ee.py
mautrix/bridge/matrix.py
mautrix/bridge/notification_disabler.py
mautrix/bridge/portal.py
mautrix/bridge/puppet.py
mautrix/bridge/user.py
mautrix/bridge/commands/__init__.py
mautrix/bridge/commands/admin.py
mautrix/bridge/commands/clean_rooms.py
mautrix/bridge/commands/crypto.py
mautrix/bridge/commands/delete_portal.py
mautrix/bridge/commands/handler.py
mautrix/bridge/commands/login_matrix.py
mautrix/bridge/commands/manhole.py
mautrix/bridge/commands/meta.py
mautrix/bridge/commands/relay.py
mautrix/bridge/state_store/__init__.py
mautrix/bridge/state_store/asyncpg.py
mautrix/client/__init__.py
mautrix/client/client.py
mautrix/client/dispatcher.py
mautrix/client/encryption_manager.py
mautrix/client/store_updater.py
mautrix/client/syncer.py
mautrix/client/api/__init__.py
mautrix/client/api/authentication.py
mautrix/client/api/base.py
mautrix/client/api/client.py
mautrix/client/api/events.py
mautrix/client/api/filtering.py
mautrix/client/api/rooms.py
mautrix/client/api/user_data.py
mautrix/client/api/modules/__init__.py
mautrix/client/api/modules/account_data.py
mautrix/client/api/modules/crypto.py
mautrix/client/api/modules/media_repository.py
mautrix/client/api/modules/misc.py
mautrix/client/api/modules/push_rules.py
mautrix/client/api/modules/room_tag.py
mautrix/client/state_store/__init__.py
mautrix-0.20.8.dist-info/LICENSE
mautrix-0.20.8.dist-info/METADATA
mautrix-0.20.8.dist-info/WHEEL
mautrix-0.20.8.dist-info/top_level.txt
mautrix-0.20.8.dist-info/RECORD
