Metadata-Version: 2.2
Name: mautrix
Version: 0.20.8
Summary: A Python 3 asyncio Matrix framework.
Home-page: https://github.com/mautrix/python
Author: Tulir Asokan
Author-email: tulir@maunium.net
Project-URL: Changelog, https://github.com/mautrix/python/blob/master/CHANGELOG.md
Classifier: Development Status :: 4 - Beta
Classifier: License :: OSI Approved :: Mozilla Public License 2.0 (MPL 2.0)
Classifier: Topic :: Communications :: Chat
Classifier: Framework :: AsyncIO
Classifier: Programming Language :: Python
Classifier: Programming Language :: Python :: 3
Classifier: Programming Language :: Python :: 3.10
Classifier: Programming Language :: Python :: 3.11
Classifier: Programming Language :: Python :: 3.12
Classifier: Programming Language :: Python :: 3.13
Requires-Python: ~=3.10
License-File: LICENSE
Requires-Dist: aiohttp<4,>=3
Requires-Dist: attrs>=18.1.0
Requires-Dist: yarl<2,>=1.5
Provides-Extra: detect-mimetype
Requires-Dist: python-magic<0.5,>=0.4.15; extra == "detect-mimetype"
Provides-Extra: lint
Requires-Dist: black~=24.1; extra == "lint"
Requires-Dist: isort; extra == "lint"
Provides-Extra: test
Requires-Dist: aiosqlite; extra == "test"
Requires-Dist: asyncpg; extra == "test"
Requires-Dist: pycryptodome; extra == "test"
Requires-Dist: pytest; extra == "test"
Requires-Dist: pytest-asyncio; extra == "test"
Requires-Dist: python-olm; extra == "test"
Requires-Dist: ruamel.yaml; extra == "test"
Requires-Dist: unpaddedbase64; extra == "test"
Provides-Extra: encryption
Requires-Dist: pycryptodome; extra == "encryption"
Requires-Dist: python-olm; extra == "encryption"
Requires-Dist: unpaddedbase64; extra == "encryption"
Dynamic: author
Dynamic: author-email
Dynamic: classifier
Dynamic: description
Dynamic: home-page
Dynamic: project-url
Dynamic: provides-extra
Dynamic: requires-dist
Dynamic: requires-python
Dynamic: summary
